MANIFEST.in
README.rst
setup.py
docs/HISTORY.txt
docs/LICENSE.GPL
docs/LICENSE.txt
plonetheme/__init__.py
plonetheme.blueberry.egg-info/PKG-INFO
plonetheme.blueberry.egg-info/SOURCES.txt
plonetheme.blueberry.egg-info/dependency_links.txt
plonetheme.blueberry.egg-info/entry_points.txt
plonetheme.blueberry.egg-info/namespace_packages.txt
plonetheme.blueberry.egg-info/not-zip-safe
plonetheme.blueberry.egg-info/requires.txt
plonetheme.blueberry.egg-info/top_level.txt
plonetheme/blueberry/__init__.py
plonetheme/blueberry/configure.zcml
plonetheme/blueberry/interfaces.py
plonetheme/blueberry/lawgiver.zcml
plonetheme/blueberry/overrides.zcml
plonetheme/blueberry/permissions.zcml
plonetheme/blueberry/plone5-resources.zcml
plonetheme/blueberry/resources.zcml
plonetheme/blueberry/testing.py
plonetheme/blueberry/utils.py
plonetheme/blueberry/baserules/__init__.py
plonetheme/blueberry/baserules/configure.zcml
plonetheme/blueberry/baserules/theme/header.xml
plonetheme/blueberry/browser/__init__.py
plonetheme/blueberry/browser/bodyclass.py
plonetheme/blueberry/browser/configure.zcml
plonetheme/blueberry/browser/dynamic_scss_resources.py
plonetheme/blueberry/browser/forms.py
plonetheme/blueberry/browser/tinymce.py
plonetheme/blueberry/browser/z3cjbot/Products.TinyMCE.skins.tinymce.plugins.plonebrowser.plonebrowser.htm.pt
plonetheme/blueberry/browser/z3cjbot/Products.TinyMCE.skins.tinymce.plugins.table.cell.htm.pt
plonetheme/blueberry/browser/z3cjbot/Products.TinyMCE.skins.tinymce.plugins.table.row.htm.pt
plonetheme/blueberry/browser/z3cjbot/Products.TinyMCE.skins.tinymce.plugins.table.table.htm.pt
plonetheme/blueberry/browser/z3cjbot/Products.TinyMCE.skins.tinymce.themes.advanced.skins.plone.content.css.dtml
plonetheme/blueberry/browser/z3cjbot/Products.TinyMCE.skins.tinymce.themes.advanced.skins.plone.dialog.css.dtml
plonetheme/blueberry/government/__init__.py
plonetheme/blueberry/government/configure.zcml
plonetheme/blueberry/government/profiles/default/metadata.xml
plonetheme/blueberry/government/profiles/default/registry.xml
plonetheme/blueberry/government/profiles/default/theme.xml
plonetheme/blueberry/government/theme/index.html
plonetheme/blueberry/government/theme/manifest.cfg
plonetheme/blueberry/government/theme/rules.xml
plonetheme/blueberry/locales/plone.tinymce-manual.pot
