Metadata-Version: 2.1
Name: plonetheme.blueberry
Version: 1.11.4
Summary: A Plone 4 / 5 theme
Home-page: https://github.com/4teamwork/plonetheme.blueberry
Author: 4teamwork AG
Author-email: mailto:info@4teamwork.ch
License: GPL2
Keywords: plone theme 4teamwork
Platform: UNKNOWN
Classifier: Environment :: Web Environment
Classifier: Framework :: Plone
Classifier: Framework :: Plone :: 4.3
Classifier: Framework :: Plone :: 5.1
Classifier: License :: OSI Approved :: GNU General Public License (GPL)
Classifier: Operating System :: OS Independent
Classifier: Programming Language :: Python
Provides-Extra: tests
